roibuddy/__init__.py
roibuddy/__main__.py
roibuddy/guiqwt_patch.py
roibuddy/importROIsWidget.py
roibuddy/roiBuddyUI.py
roibuddy/roi_buddy.py
roibuddy/icons/colorize.png
roibuddy/icons/document-save-5.png
roibuddy/icons/document-save-all.png
roibuddy/icons/document-sign.png
roibuddy/icons/edit-cut.png
roibuddy/icons/edit-delete-2.png
roibuddy/icons/edit.png
roibuddy/icons/flag-green.png
roibuddy/icons/flag-red.png
roibuddy/icons/insert-link.png
roibuddy/icons/roi-buddy.ico
roibuddy/icons/transform-move.png
roibuddy-1.0.1.dist-info/DESCRIPTION.rst
roibuddy-1.0.1.dist-info/METADATA
roibuddy-1.0.1.dist-info/RECORD
roibuddy-1.0.1.dist-info/WHEEL
roibuddy-1.0.1.dist-info/entry_points.txt
roibuddy-1.0.1.dist-info/metadata.json
roibuddy-1.0.1.dist-info/top_level.txt
