Metadata-Version: 2.0
Name: roibuddy
Version: 1.0.1
Summary: GUI for editing segmentations when using SIMA
Home-page: http://www.losonczylab.org/sima/
Author: The SIMA Development Team
Author-email: software@losonczylab.org
License: GNU GPLv2
Keywords: imaging microscopy neuroscience segmentation
Platform: Linux
Platform: Mac OS-X
Platform: Windows
Classifier: Development Status :: 4 - Beta
Classifier: Intended Audience :: Science/Research
Classifier: License :: OSI Approved :: GNU General Public License v2 or later (GPLv2+)
Classifier: Operating System :: MacOS
Classifier: Operating System :: Microsoft :: Windows
Classifier: Operating System :: POSIX
Classifier: Operating System :: Unix
Classifier: Programming Language :: Python
Classifier: Topic :: Scientific/Engineering
Requires-Dist: guidata (>=1.7.0)
Requires-Dist: guiqwt (>=3.0.0)
Requires-Dist: pythonqwt
Requires-Dist: sima (>=1.0.0)
